<?xml version="1.0" encoding="UTF-8"?>
<sv:node sv:name="resize" xmlns:sv="http://www.jcp.org/jcr/sv/1.0" xmlns:xsi="http://www.w3.org/2001/XMLSchema-instance">
  <sv:property sv:name="jcr:primaryType" sv:type="Name">
    <sv:value>mgnl:contentNode</sv:value>
  </sv:property>
  <sv:property sv:name="jcr:uuid" sv:type="String">
    <sv:value>8dd59b94-b8d7-44ba-b757-aa91bd233d03</sv:value>
  </sv:property>
  <sv:property sv:name="class" sv:type="String">
    <sv:value>edu.txstate.its.gato.ImagingModuleResizer</sv:value>
  </sv:property>
  <sv:property sv:name="jcr:createdBy" sv:type="String">
    <sv:value>admin</sv:value>
  </sv:property>
  <sv:property sv:name="mgnl:created" sv:type="Date">
    <sv:value>2015-09-14T16:57:34.481-05:00</sv:value>
  </sv:property>
  <sv:property sv:name="mgnl:createdBy" sv:type="String">
    <sv:value>nw13</sv:value>
  </sv:property>
  <sv:property sv:name="mgnl:lastModified" sv:type="Date">
    <sv:value>2015-09-15T13:33:17.305-05:00</sv:value>
  </sv:property>
  <sv:property sv:name="mgnl:lastModifiedBy" sv:type="String">
    <sv:value>nw13</sv:value>
  </sv:property>
</sv:node>
