<?xml version="1.0" encoding="UTF-8"?>
<sv:node sv:name="restorePreviousVersion" xmlns:sv="http://www.jcp.org/jcr/sv/1.0" xmlns:xsi="http://www.w3.org/2001/XMLSchema-instance">
  <sv:property sv:name="jcr:primaryType" sv:type="Name">
    <sv:value>mgnl:contentNode</sv:value>
  </sv:property>
  <sv:property sv:name="jcr:mixinTypes" sv:type="Name" sv:multiple="true">
    <sv:value>mix:lockable</sv:value>
  </sv:property>
  <sv:property sv:name="jcr:uuid" sv:type="String">
    <sv:value>445f3ec1-35ee-4881-97dd-9bb37728629b</sv:value>
  </sv:property>
  <sv:property sv:name="class" sv:type="String">
    <sv:value>info.magnolia.ui.contentapp.browser.action.RestoreItemPreviousVersionActionDefinition</sv:value>
  </sv:property>
  <sv:property sv:name="icon" sv:type="String">
    <sv:value>icon-undo</sv:value>
  </sv:property>
  <sv:property sv:name="jcr:createdBy" sv:type="String">
    <sv:value>admin</sv:value>
  </sv:property>
  <sv:property sv:name="mgnl:lastModified" sv:type="Date">
    <sv:value>2016-07-11T11:39:44.496-05:00</sv:value>
  </sv:property>
  <sv:property sv:name="mgnl:lastModifiedBy" sv:type="String">
    <sv:value>a_f269</sv:value>
  </sv:property>
  <sv:property sv:name="notifyUser" sv:type="String">
    <sv:value>false</sv:value>
  </sv:property>
  <sv:node sv:name="availability">
    <sv:property sv:name="jcr:primaryType" sv:type="Name">
      <sv:value>mgnl:contentNode</sv:value>
    </sv:property>
    <sv:property sv:name="jcr:uuid" sv:type="String">
      <sv:value>494eba57-5b43-4bc1-b641-adacc028abe2</sv:value>
    </sv:property>
    <sv:property sv:name="jcr:createdBy" sv:type="String">
      <sv:value>admin</sv:value>
    </sv:property>
    <sv:property sv:name="mgnl:created" sv:type="Date">
      <sv:value>2014-07-03T10:31:01.761+02:00</sv:value>
    </sv:property>
    <sv:property sv:name="mgnl:createdBy" sv:type="String">
      <sv:value>superuser</sv:value>
    </sv:property>
    <sv:property sv:name="mgnl:lastModified" sv:type="Date">
      <sv:value>2014-07-03T10:31:27.593+02:00</sv:value>
    </sv:property>
    <sv:property sv:name="mgnl:lastModifiedBy" sv:type="String">
      <sv:value>superuser</sv:value>
    </sv:property>
    <sv:property sv:name="multiple" sv:type="String">
      <sv:value>true</sv:value>
    </sv:property>
    <sv:property sv:name="writePermissionRequired" sv:type="Boolean">
      <sv:value>true</sv:value>
    </sv:property>
  </sv:node>
</sv:node>
