<?xml version="1.0" encoding="UTF-8"?>
<sv:node sv:name="global-links" xmlns:sv="http://www.jcp.org/jcr/sv/1.0" xmlns:xsi="http://www.w3.org/2001/XMLSchema-instance">
  <sv:property sv:name="jcr:primaryType" sv:type="Name">
    <sv:value>mgnl:content</sv:value>
  </sv:property>
  <sv:property sv:name="jcr:uuid" sv:type="String">
    <sv:value>e50e234f-4164-4530-972e-8b408672abf5</sv:value>
  </sv:property>
  <sv:property sv:name="jcr:createdBy" sv:type="String">
    <sv:value>admin</sv:value>
  </sv:property>
  <sv:property sv:name="mgnl:activationStatus" sv:type="Boolean">
    <sv:value>true</sv:value>
  </sv:property>
  <sv:property sv:name="mgnl:created" sv:type="Date">
    <sv:value>2015-12-07T17:00:31.964-06:00</sv:value>
  </sv:property>
  <sv:property sv:name="mgnl:createdBy" sv:type="String">
    <sv:value>cj32</sv:value>
  </sv:property>
  <sv:property sv:name="mgnl:lastActivated" sv:type="Date">
    <sv:value>2015-12-16T09:27:51.617-06:00</sv:value>
  </sv:property>
  <sv:property sv:name="mgnl:lastActivatedBy" sv:type="String">
    <sv:value>superuser</sv:value>
  </sv:property>
  <sv:property sv:name="mgnl:lastModified" sv:type="Date">
    <sv:value>2015-12-07T17:00:31.964-06:00</sv:value>
  </sv:property>
  <sv:property sv:name="mgnl:lastModifiedBy" sv:type="String">
    <sv:value>cj32</sv:value>
  </sv:property>
  <sv:node sv:name="superGroup1">
    <sv:property sv:name="jcr:primaryType" sv:type="Name">
      <sv:value>mgnl:content</sv:value>
    </sv:property>
    <sv:property sv:name="jcr:uuid" sv:type="String">
      <sv:value>544842a2-e153-4d3b-b40d-ed517ae8cc30</sv:value>
    </sv:property>
    <sv:property sv:name="jcr:createdBy" sv:type="String">
      <sv:value>admin</sv:value>
    </sv:property>
    <sv:property sv:name="mgnl:activationStatus" sv:type="Boolean">
      <sv:value>true</sv:value>
    </sv:property>
    <sv:property sv:name="mgnl:created" sv:type="Date">
      <sv:value>2015-11-06T12:39:48.207-06:00</sv:value>
    </sv:property>
    <sv:property sv:name="mgnl:createdBy" sv:type="String">
      <sv:value>a_f269</sv:value>
    </sv:property>
    <sv:property sv:name="mgnl:lastActivated" sv:type="Date">
      <sv:value>2016-01-01T18:31:30.798-06:00</sv:value>
    </sv:property>
    <sv:property sv:name="mgnl:lastActivatedBy" sv:type="String">
      <sv:value>superuser</sv:value>
    </sv:property>
    <sv:property sv:name="mgnl:lastModified" sv:type="Date">
      <sv:value>2015-11-06T12:39:48.207-06:00</sv:value>
    </sv:property>
    <sv:property sv:name="mgnl:lastModifiedBy" sv:type="String">
      <sv:value>a_f269</sv:value>
    </sv:property>
    <sv:property sv:name="text" sv:type="String">
      <sv:value>Left Super User Bar</sv:value>
    </sv:property>
    <sv:node sv:name="0">
      <sv:property sv:name="jcr:primaryType" sv:type="Name">
        <sv:value>mgnl:component</sv:value>
      </sv:property>
      <sv:property sv:name="jcr:uuid" sv:type="String">
        <sv:value>71ce0bd0-8ea1-459f-b5db-38f9c1489d47</sv:value>
      </sv:property>
      <sv:property sv:name="jcr:createdBy" sv:type="String">
        <sv:value>admin</sv:value>
      </sv:property>
      <sv:property sv:name="link" sv:type="String">
        <sv:value>http://www.txstate.edu/about</sv:value>
      </sv:property>
      <sv:property sv:name="mgnl:activationStatus" sv:type="Boolean">
        <sv:value>true</sv:value>
      </sv:property>
      <sv:property sv:name="mgnl:created" sv:type="Date">
        <sv:value>2015-11-06T12:44:25.102-06:00</sv:value>
      </sv:property>
      <sv:property sv:name="mgnl:createdBy" sv:type="String">
        <sv:value>a_f269</sv:value>
      </sv:property>
      <sv:property sv:name="mgnl:lastActivated" sv:type="Date">
        <sv:value>2016-01-01T18:31:30.798-06:00</sv:value>
      </sv:property>
      <sv:property sv:name="mgnl:lastActivatedBy" sv:type="String">
        <sv:value>superuser</sv:value>
      </sv:property>
      <sv:property sv:name="mgnl:lastModified" sv:type="Date">
        <sv:value>2015-11-06T12:44:25.102-06:00</sv:value>
      </sv:property>
      <sv:property sv:name="mgnl:lastModifiedBy" sv:type="String">
        <sv:value>a_f269</sv:value>
      </sv:property>
      <sv:property sv:name="mgnl:template" sv:type="String">
        <sv:value>gato-template:components/link</sv:value>
      </sv:property>
      <sv:property sv:name="text" sv:type="String">
        <sv:value>About</sv:value>
      </sv:property>
    </sv:node>
    <sv:node sv:name="00">
      <sv:property sv:name="jcr:primaryType" sv:type="Name">
        <sv:value>mgnl:component</sv:value>
      </sv:property>
      <sv:property sv:name="jcr:uuid" sv:type="String">
        <sv:value>9ca097da-e2ba-4a23-b27e-a57d40dc57e7</sv:value>
      </sv:property>
      <sv:property sv:name="jcr:createdBy" sv:type="String">
        <sv:value>admin</sv:value>
      </sv:property>
      <sv:property sv:name="link" sv:type="String">
        <sv:value>http://www.txstatebobcats.com/</sv:value>
      </sv:property>
      <sv:property sv:name="mgnl:activationStatus" sv:type="Boolean">
        <sv:value>true</sv:value>
      </sv:property>
      <sv:property sv:name="mgnl:created" sv:type="Date">
        <sv:value>2015-11-06T12:44:50.433-06:00</sv:value>
      </sv:property>
      <sv:property sv:name="mgnl:createdBy" sv:type="String">
        <sv:value>a_f269</sv:value>
      </sv:property>
      <sv:property sv:name="mgnl:lastActivated" sv:type="Date">
        <sv:value>2016-01-01T18:31:30.798-06:00</sv:value>
      </sv:property>
      <sv:property sv:name="mgnl:lastActivatedBy" sv:type="String">
        <sv:value>superuser</sv:value>
      </sv:property>
      <sv:property sv:name="mgnl:lastModified" sv:type="Date">
        <sv:value>2015-11-06T12:44:50.433-06:00</sv:value>
      </sv:property>
      <sv:property sv:name="mgnl:lastModifiedBy" sv:type="String">
        <sv:value>a_f269</sv:value>
      </sv:property>
      <sv:property sv:name="mgnl:template" sv:type="String">
        <sv:value>gato-template:components/link</sv:value>
      </sv:property>
      <sv:property sv:name="text" sv:type="String">
        <sv:value>Athletics</sv:value>
      </sv:property>
    </sv:node>
    <sv:node sv:name="01">
      <sv:property sv:name="jcr:primaryType" sv:type="Name">
        <sv:value>mgnl:component</sv:value>
      </sv:property>
      <sv:property sv:name="jcr:uuid" sv:type="String">
        <sv:value>d14eca68-fb37-4ac4-bb90-46dd6639180f</sv:value>
      </sv:property>
      <sv:property sv:name="jcr:createdBy" sv:type="String">
        <sv:value>admin</sv:value>
      </sv:property>
      <sv:property sv:name="link" sv:type="String">
        <sv:value>http://www.ua.txstate.edu/give-to-texas-state.html</sv:value>
      </sv:property>
      <sv:property sv:name="mgnl:activationStatus" sv:type="Boolean">
        <sv:value>true</sv:value>
      </sv:property>
      <sv:property sv:name="mgnl:comment" sv:type="String">
        <sv:value/>
      </sv:property>
      <sv:property sv:name="mgnl:created" sv:type="Date">
        <sv:value>2015-11-06T12:45:06.898-06:00</sv:value>
      </sv:property>
      <sv:property sv:name="mgnl:createdBy" sv:type="String">
        <sv:value>a_f269</sv:value>
      </sv:property>
      <sv:property sv:name="mgnl:lastActivated" sv:type="Date">
        <sv:value>2016-01-27T10:07:26.459-06:00</sv:value>
      </sv:property>
      <sv:property sv:name="mgnl:lastActivatedBy" sv:type="String">
        <sv:value>mwe12</sv:value>
      </sv:property>
      <sv:property sv:name="mgnl:lastModified" sv:type="Date">
        <sv:value>2015-11-06T12:45:06.898-06:00</sv:value>
      </sv:property>
      <sv:property sv:name="mgnl:lastModifiedBy" sv:type="String">
        <sv:value>a_f269</sv:value>
      </sv:property>
      <sv:property sv:name="mgnl:template" sv:type="String">
        <sv:value>gato-template:components/link</sv:value>
      </sv:property>
      <sv:property sv:name="text" sv:type="String">
        <sv:value>Give</sv:value>
      </sv:property>
    </sv:node>
    <sv:node sv:name="02">
      <sv:property sv:name="jcr:primaryType" sv:type="Name">
        <sv:value>mgnl:component</sv:value>
      </sv:property>
      <sv:property sv:name="jcr:uuid" sv:type="String">
        <sv:value>2a709f9a-8841-4ca5-bac1-5cf522e2e7de</sv:value>
      </sv:property>
      <sv:property sv:name="jcr:createdBy" sv:type="String">
        <sv:value>admin</sv:value>
      </sv:property>
      <sv:property sv:name="link" sv:type="String">
        <sv:value>http://www.library.txstate.edu/</sv:value>
      </sv:property>
      <sv:property sv:name="mgnl:activationStatus" sv:type="Boolean">
        <sv:value>true</sv:value>
      </sv:property>
      <sv:property sv:name="mgnl:created" sv:type="Date">
        <sv:value>2015-11-06T12:42:31.308-06:00</sv:value>
      </sv:property>
      <sv:property sv:name="mgnl:createdBy" sv:type="String">
        <sv:value>a_f269</sv:value>
      </sv:property>
      <sv:property sv:name="mgnl:lastActivated" sv:type="Date">
        <sv:value>2016-01-01T18:31:30.798-06:00</sv:value>
      </sv:property>
      <sv:property sv:name="mgnl:lastActivatedBy" sv:type="String">
        <sv:value>superuser</sv:value>
      </sv:property>
      <sv:property sv:name="mgnl:lastModified" sv:type="Date">
        <sv:value>2015-11-06T12:42:31.308-06:00</sv:value>
      </sv:property>
      <sv:property sv:name="mgnl:lastModifiedBy" sv:type="String">
        <sv:value>a_f269</sv:value>
      </sv:property>
      <sv:property sv:name="mgnl:template" sv:type="String">
        <sv:value>gato-template:components/link</sv:value>
      </sv:property>
      <sv:property sv:name="text" sv:type="String">
        <sv:value>Library</sv:value>
      </sv:property>
    </sv:node>
    <sv:node sv:name="03">
      <sv:property sv:name="jcr:primaryType" sv:type="Name">
        <sv:value>mgnl:component</sv:value>
      </sv:property>
      <sv:property sv:name="jcr:uuid" sv:type="String">
        <sv:value>fdb41511-0ef7-4324-aabd-1c92fe9eb67f</sv:value>
      </sv:property>
      <sv:property sv:name="jcr:createdBy" sv:type="String">
        <sv:value>admin</sv:value>
      </sv:property>
      <sv:property sv:name="link" sv:type="String">
        <sv:value>http://www.maps.txstate.edu/</sv:value>
      </sv:property>
      <sv:property sv:name="mgnl:activationStatus" sv:type="Boolean">
        <sv:value>true</sv:value>
      </sv:property>
      <sv:property sv:name="mgnl:comment" sv:type="String">
        <sv:value/>
      </sv:property>
      <sv:property sv:name="mgnl:created" sv:type="Date">
        <sv:value>2015-11-06T12:43:17.975-06:00</sv:value>
      </sv:property>
      <sv:property sv:name="mgnl:createdBy" sv:type="String">
        <sv:value>a_f269</sv:value>
      </sv:property>
      <sv:property sv:name="mgnl:lastActivated" sv:type="Date">
        <sv:value>2016-01-01T18:31:30.798-06:00</sv:value>
      </sv:property>
      <sv:property sv:name="mgnl:lastActivatedBy" sv:type="String">
        <sv:value>superuser</sv:value>
      </sv:property>
      <sv:property sv:name="mgnl:lastModified" sv:type="Date">
        <sv:value>2015-11-06T12:43:17.975-06:00</sv:value>
      </sv:property>
      <sv:property sv:name="mgnl:lastModifiedBy" sv:type="String">
        <sv:value>a_f269</sv:value>
      </sv:property>
      <sv:property sv:name="mgnl:template" sv:type="String">
        <sv:value>gato-template:components/link</sv:value>
      </sv:property>
      <sv:property sv:name="text" sv:type="String">
        <sv:value>Maps</sv:value>
      </sv:property>
    </sv:node>
    <sv:node sv:name="04">
      <sv:property sv:name="jcr:primaryType" sv:type="Name">
        <sv:value>mgnl:component</sv:value>
      </sv:property>
      <sv:property sv:name="jcr:uuid" sv:type="String">
        <sv:value>34324964-d741-43e7-aeff-72e4f9f2980e</sv:value>
      </sv:property>
      <sv:property sv:name="jcr:createdBy" sv:type="String">
        <sv:value>admin</sv:value>
      </sv:property>
      <sv:property sv:name="link" sv:type="String">
        <sv:value>http://www.rrc.txstate.edu/</sv:value>
      </sv:property>
      <sv:property sv:name="mgnl:activationStatus" sv:type="Boolean">
        <sv:value>true</sv:value>
      </sv:property>
      <sv:property sv:name="mgnl:comment" sv:type="String">
        <sv:value/>
      </sv:property>
      <sv:property sv:name="mgnl:created" sv:type="Date">
        <sv:value>2015-12-18T12:27:34.989-06:00</sv:value>
      </sv:property>
      <sv:property sv:name="mgnl:createdBy" sv:type="String">
        <sv:value>rp41</sv:value>
      </sv:property>
      <sv:property sv:name="mgnl:lastActivated" sv:type="Date">
        <sv:value>2016-01-01T18:31:30.799-06:00</sv:value>
      </sv:property>
      <sv:property sv:name="mgnl:lastActivatedBy" sv:type="String">
        <sv:value>superuser</sv:value>
      </sv:property>
      <sv:property sv:name="mgnl:lastModified" sv:type="Date">
        <sv:value>2015-12-18T12:27:34.989-06:00</sv:value>
      </sv:property>
      <sv:property sv:name="mgnl:lastModifiedBy" sv:type="String">
        <sv:value>rp41</sv:value>
      </sv:property>
      <sv:property sv:name="text" sv:type="String">
        <sv:value>Round Rock</sv:value>
      </sv:property>
    </sv:node>
  </sv:node>
  <sv:node sv:name="superGroup2">
    <sv:property sv:name="jcr:primaryType" sv:type="Name">
      <sv:value>mgnl:content</sv:value>
    </sv:property>
    <sv:property sv:name="jcr:uuid" sv:type="String">
      <sv:value>09978cd9-a92c-4852-94f7-ce209ed118ad</sv:value>
    </sv:property>
    <sv:property sv:name="jcr:createdBy" sv:type="String">
      <sv:value>admin</sv:value>
    </sv:property>
    <sv:property sv:name="mgnl:activationStatus" sv:type="Boolean">
      <sv:value>true</sv:value>
    </sv:property>
    <sv:property sv:name="mgnl:created" sv:type="Date">
      <sv:value>2015-11-06T12:39:48.861-06:00</sv:value>
    </sv:property>
    <sv:property sv:name="mgnl:createdBy" sv:type="String">
      <sv:value>a_f269</sv:value>
    </sv:property>
    <sv:property sv:name="mgnl:lastActivated" sv:type="Date">
      <sv:value>2016-01-01T18:31:35.319-06:00</sv:value>
    </sv:property>
    <sv:property sv:name="mgnl:lastActivatedBy" sv:type="String">
      <sv:value>superuser</sv:value>
    </sv:property>
    <sv:property sv:name="mgnl:lastModified" sv:type="Date">
      <sv:value>2015-11-06T12:39:48.861-06:00</sv:value>
    </sv:property>
    <sv:property sv:name="mgnl:lastModifiedBy" sv:type="String">
      <sv:value>a_f269</sv:value>
    </sv:property>
    <sv:property sv:name="text" sv:type="String">
      <sv:value>Right Super User Bar</sv:value>
    </sv:property>
    <sv:node sv:name="0">
      <sv:property sv:name="jcr:primaryType" sv:type="Name">
        <sv:value>mgnl:component</sv:value>
      </sv:property>
      <sv:property sv:name="jcr:uuid" sv:type="String">
        <sv:value>150dcd55-e6ef-47cb-81de-088d0eb33117</sv:value>
      </sv:property>
      <sv:property sv:name="jcr:createdBy" sv:type="String">
        <sv:value>admin</sv:value>
      </sv:property>
      <sv:property sv:name="link" sv:type="String">
        <sv:value>https://bobcatmail.txstate.edu</sv:value>
      </sv:property>
      <sv:property sv:name="mgnl:activationStatus" sv:type="Boolean">
        <sv:value>true</sv:value>
      </sv:property>
      <sv:property sv:name="mgnl:created" sv:type="Date">
        <sv:value>2015-11-06T12:46:36.995-06:00</sv:value>
      </sv:property>
      <sv:property sv:name="mgnl:createdBy" sv:type="String">
        <sv:value>a_f269</sv:value>
      </sv:property>
      <sv:property sv:name="mgnl:lastActivated" sv:type="Date">
        <sv:value>2016-01-01T18:31:35.319-06:00</sv:value>
      </sv:property>
      <sv:property sv:name="mgnl:lastActivatedBy" sv:type="String">
        <sv:value>superuser</sv:value>
      </sv:property>
      <sv:property sv:name="mgnl:lastModified" sv:type="Date">
        <sv:value>2015-11-06T12:46:36.995-06:00</sv:value>
      </sv:property>
      <sv:property sv:name="mgnl:lastModifiedBy" sv:type="String">
        <sv:value>a_f269</sv:value>
      </sv:property>
      <sv:property sv:name="mgnl:template" sv:type="String">
        <sv:value>gato-template:components/link</sv:value>
      </sv:property>
      <sv:property sv:name="text" sv:type="String">
        <sv:value>BobcatMail</sv:value>
      </sv:property>
    </sv:node>
    <sv:node sv:name="00">
      <sv:property sv:name="jcr:primaryType" sv:type="Name">
        <sv:value>mgnl:component</sv:value>
      </sv:property>
      <sv:property sv:name="jcr:uuid" sv:type="String">
        <sv:value>fa66fa1e-ab41-4fb0-8f6d-da9562286e9c</sv:value>
      </sv:property>
      <sv:property sv:name="jcr:createdBy" sv:type="String">
        <sv:value>admin</sv:value>
      </sv:property>
      <sv:property sv:name="link" sv:type="String">
        <sv:value>http://catsweb.txstate.edu/catsweb/index.htm</sv:value>
      </sv:property>
      <sv:property sv:name="mgnl:activationStatus" sv:type="Boolean">
        <sv:value>true</sv:value>
      </sv:property>
      <sv:property sv:name="mgnl:created" sv:type="Date">
        <sv:value>2015-11-06T12:46:48.636-06:00</sv:value>
      </sv:property>
      <sv:property sv:name="mgnl:createdBy" sv:type="String">
        <sv:value>a_f269</sv:value>
      </sv:property>
      <sv:property sv:name="mgnl:lastActivated" sv:type="Date">
        <sv:value>2016-01-01T18:31:35.319-06:00</sv:value>
      </sv:property>
      <sv:property sv:name="mgnl:lastActivatedBy" sv:type="String">
        <sv:value>superuser</sv:value>
      </sv:property>
      <sv:property sv:name="mgnl:lastModified" sv:type="Date">
        <sv:value>2015-11-06T12:46:48.636-06:00</sv:value>
      </sv:property>
      <sv:property sv:name="mgnl:lastModifiedBy" sv:type="String">
        <sv:value>a_f269</sv:value>
      </sv:property>
      <sv:property sv:name="mgnl:template" sv:type="String">
        <sv:value>gato-template:components/link</sv:value>
      </sv:property>
      <sv:property sv:name="text" sv:type="String">
        <sv:value>CatsWeb</sv:value>
      </sv:property>
    </sv:node>
    <sv:node sv:name="01">
      <sv:property sv:name="jcr:primaryType" sv:type="Name">
        <sv:value>mgnl:component</sv:value>
      </sv:property>
      <sv:property sv:name="jcr:uuid" sv:type="String">
        <sv:value>676b0fb5-958a-468d-9f21-1dce56aa495d</sv:value>
      </sv:property>
      <sv:property sv:name="jcr:createdBy" sv:type="String">
        <sv:value>admin</sv:value>
      </sv:property>
      <sv:property sv:name="link" sv:type="String">
        <sv:value>https://tracs.txstate.edu/portal/login</sv:value>
      </sv:property>
      <sv:property sv:name="mgnl:activationStatus" sv:type="Boolean">
        <sv:value>true</sv:value>
      </sv:property>
      <sv:property sv:name="mgnl:created" sv:type="Date">
        <sv:value>2015-11-06T12:48:01.858-06:00</sv:value>
      </sv:property>
      <sv:property sv:name="mgnl:createdBy" sv:type="String">
        <sv:value>a_f269</sv:value>
      </sv:property>
      <sv:property sv:name="mgnl:lastActivated" sv:type="Date">
        <sv:value>2016-01-01T18:31:35.319-06:00</sv:value>
      </sv:property>
      <sv:property sv:name="mgnl:lastActivatedBy" sv:type="String">
        <sv:value>superuser</sv:value>
      </sv:property>
      <sv:property sv:name="mgnl:lastModified" sv:type="Date">
        <sv:value>2015-11-06T12:48:01.858-06:00</sv:value>
      </sv:property>
      <sv:property sv:name="mgnl:lastModifiedBy" sv:type="String">
        <sv:value>a_f269</sv:value>
      </sv:property>
      <sv:property sv:name="mgnl:template" sv:type="String">
        <sv:value>gato-template:components/link</sv:value>
      </sv:property>
      <sv:property sv:name="text" sv:type="String">
        <sv:value>Tracs</sv:value>
      </sv:property>
    </sv:node>
  </sv:node>
  <sv:node sv:name="superGroup3">
    <sv:property sv:name="jcr:primaryType" sv:type="Name">
      <sv:value>mgnl:content</sv:value>
    </sv:property>
    <sv:property sv:name="jcr:uuid" sv:type="String">
      <sv:value>aec9e5b8-2507-48b0-bbb6-708eefa727fe</sv:value>
    </sv:property>
    <sv:property sv:name="jcr:createdBy" sv:type="String">
      <sv:value>admin</sv:value>
    </sv:property>
    <sv:property sv:name="mgnl:activationStatus" sv:type="Boolean">
      <sv:value>true</sv:value>
    </sv:property>
    <sv:property sv:name="mgnl:created" sv:type="Date">
      <sv:value>2015-11-06T12:39:49.485-06:00</sv:value>
    </sv:property>
    <sv:property sv:name="mgnl:createdBy" sv:type="String">
      <sv:value>a_f269</sv:value>
    </sv:property>
    <sv:property sv:name="mgnl:lastActivated" sv:type="Date">
      <sv:value>2016-02-15T11:30:00.799-06:00</sv:value>
    </sv:property>
    <sv:property sv:name="mgnl:lastActivatedBy" sv:type="String">
      <sv:value>superuser</sv:value>
    </sv:property>
    <sv:property sv:name="mgnl:lastModified" sv:type="Date">
      <sv:value>2016-02-15T11:29:55.766-06:00</sv:value>
    </sv:property>
    <sv:property sv:name="mgnl:lastModifiedBy" sv:type="String">
      <sv:value>mwe12</sv:value>
    </sv:property>
    <sv:property sv:name="text" sv:type="String">
      <sv:value>More Tools</sv:value>
    </sv:property>
    <sv:node sv:name="0">
      <sv:property sv:name="jcr:primaryType" sv:type="Name">
        <sv:value>mgnl:component</sv:value>
      </sv:property>
      <sv:property sv:name="jcr:uuid" sv:type="String">
        <sv:value>3efdfb70-3e9c-4b75-8ac5-ebfb697b54ae</sv:value>
      </sv:property>
      <sv:property sv:name="jcr:createdBy" sv:type="String">
        <sv:value>admin</sv:value>
      </sv:property>
      <sv:property sv:name="link" sv:type="String">
        <sv:value>https://ibis.sap.txstate.edu/irj/portal</sv:value>
      </sv:property>
      <sv:property sv:name="mgnl:activationStatus" sv:type="Boolean">
        <sv:value>true</sv:value>
      </sv:property>
      <sv:property sv:name="mgnl:created" sv:type="Date">
        <sv:value>2015-11-06T12:49:29.717-06:00</sv:value>
      </sv:property>
      <sv:property sv:name="mgnl:createdBy" sv:type="String">
        <sv:value>a_f269</sv:value>
      </sv:property>
      <sv:property sv:name="mgnl:lastActivated" sv:type="Date">
        <sv:value>2016-02-15T11:30:00.800-06:00</sv:value>
      </sv:property>
      <sv:property sv:name="mgnl:lastActivatedBy" sv:type="String">
        <sv:value>superuser</sv:value>
      </sv:property>
      <sv:property sv:name="mgnl:lastModified" sv:type="Date">
        <sv:value>2015-11-06T12:49:29.717-06:00</sv:value>
      </sv:property>
      <sv:property sv:name="mgnl:lastModifiedBy" sv:type="String">
        <sv:value>a_f269</sv:value>
      </sv:property>
      <sv:property sv:name="mgnl:template" sv:type="String">
        <sv:value>gato-template:components/link</sv:value>
      </sv:property>
      <sv:property sv:name="text" sv:type="String">
        <sv:value>SAP Portal</sv:value>
      </sv:property>
    </sv:node>
    <sv:node sv:name="00">
      <sv:property sv:name="jcr:primaryType" sv:type="Name">
        <sv:value>mgnl:component</sv:value>
      </sv:property>
      <sv:property sv:name="jcr:uuid" sv:type="String">
        <sv:value>a242224c-45ed-4d8c-b133-107bd7961240</sv:value>
      </sv:property>
      <sv:property sv:name="jcr:createdBy" sv:type="String">
        <sv:value>admin</sv:value>
      </sv:property>
      <sv:property sv:name="link" sv:type="String">
        <sv:value>http://www.txstate.edu/pay-tuition</sv:value>
      </sv:property>
      <sv:property sv:name="mgnl:activationStatus" sv:type="Boolean">
        <sv:value>true</sv:value>
      </sv:property>
      <sv:property sv:name="mgnl:comment" sv:type="String">
        <sv:value/>
      </sv:property>
      <sv:property sv:name="mgnl:created" sv:type="Date">
        <sv:value>2015-11-06T12:49:56.440-06:00</sv:value>
      </sv:property>
      <sv:property sv:name="mgnl:createdBy" sv:type="String">
        <sv:value>a_f269</sv:value>
      </sv:property>
      <sv:property sv:name="mgnl:lastActivated" sv:type="Date">
        <sv:value>2016-02-15T11:30:00.800-06:00</sv:value>
      </sv:property>
      <sv:property sv:name="mgnl:lastActivatedBy" sv:type="String">
        <sv:value>superuser</sv:value>
      </sv:property>
      <sv:property sv:name="mgnl:lastModified" sv:type="Date">
        <sv:value>2015-11-06T12:49:56.440-06:00</sv:value>
      </sv:property>
      <sv:property sv:name="mgnl:lastModifiedBy" sv:type="String">
        <sv:value>a_f269</sv:value>
      </sv:property>
      <sv:property sv:name="mgnl:template" sv:type="String">
        <sv:value>gato-template:components/link</sv:value>
      </sv:property>
      <sv:property sv:name="text" sv:type="String">
        <sv:value>Pay Tuition</sv:value>
      </sv:property>
    </sv:node>
    <sv:node sv:name="01">
      <sv:property sv:name="jcr:primaryType" sv:type="Name">
        <sv:value>mgnl:component</sv:value>
      </sv:property>
      <sv:property sv:name="jcr:uuid" sv:type="String">
        <sv:value>3e2477b0-c8fe-4561-b233-d42db271334f</sv:value>
      </sv:property>
      <sv:property sv:name="jcr:createdBy" sv:type="String">
        <sv:value>admin</sv:value>
      </sv:property>
      <sv:property sv:name="link" sv:type="String">
        <sv:value>https://tim.txstate.edu/onlinetoolkit/CustomLogin</sv:value>
      </sv:property>
      <sv:property sv:name="mgnl:activationStatus" sv:type="Boolean">
        <sv:value>true</sv:value>
      </sv:property>
      <sv:property sv:name="mgnl:created" sv:type="Date">
        <sv:value>2015-11-06T12:49:56.865-06:00</sv:value>
      </sv:property>
      <sv:property sv:name="mgnl:createdBy" sv:type="String">
        <sv:value>a_f269</sv:value>
      </sv:property>
      <sv:property sv:name="mgnl:lastActivated" sv:type="Date">
        <sv:value>2016-02-15T11:30:00.800-06:00</sv:value>
      </sv:property>
      <sv:property sv:name="mgnl:lastActivatedBy" sv:type="String">
        <sv:value>superuser</sv:value>
      </sv:property>
      <sv:property sv:name="mgnl:lastModified" sv:type="Date">
        <sv:value>2015-11-06T12:49:56.865-06:00</sv:value>
      </sv:property>
      <sv:property sv:name="mgnl:lastModifiedBy" sv:type="String">
        <sv:value>a_f269</sv:value>
      </sv:property>
      <sv:property sv:name="mgnl:template" sv:type="String">
        <sv:value>gato-template:components/link</sv:value>
      </sv:property>
      <sv:property sv:name="text" sv:type="String">
        <sv:value>Online Toolkit</sv:value>
      </sv:property>
    </sv:node>
    <sv:node sv:name="02">
      <sv:property sv:name="jcr:primaryType" sv:type="Name">
        <sv:value>mgnl:component</sv:value>
      </sv:property>
      <sv:property sv:name="jcr:uuid" sv:type="String">
        <sv:value>39d9b41f-cb68-40f0-ac71-f59d0b02c27f</sv:value>
      </sv:property>
      <sv:property sv:name="jcr:createdBy" sv:type="String">
        <sv:value>admin</sv:value>
      </sv:property>
      <sv:property sv:name="link" sv:type="String">
        <sv:value>https://eportfolio.txstate.edu/</sv:value>
      </sv:property>
      <sv:property sv:name="mgnl:activationStatus" sv:type="Boolean">
        <sv:value>true</sv:value>
      </sv:property>
      <sv:property sv:name="mgnl:created" sv:type="Date">
        <sv:value>2015-11-06T12:49:57.239-06:00</sv:value>
      </sv:property>
      <sv:property sv:name="mgnl:createdBy" sv:type="String">
        <sv:value>a_f269</sv:value>
      </sv:property>
      <sv:property sv:name="mgnl:lastActivated" sv:type="Date">
        <sv:value>2016-02-15T11:30:00.800-06:00</sv:value>
      </sv:property>
      <sv:property sv:name="mgnl:lastActivatedBy" sv:type="String">
        <sv:value>superuser</sv:value>
      </sv:property>
      <sv:property sv:name="mgnl:lastModified" sv:type="Date">
        <sv:value>2015-11-06T12:49:57.239-06:00</sv:value>
      </sv:property>
      <sv:property sv:name="mgnl:lastModifiedBy" sv:type="String">
        <sv:value>a_f269</sv:value>
      </sv:property>
      <sv:property sv:name="mgnl:template" sv:type="String">
        <sv:value>gato-template:components/link</sv:value>
      </sv:property>
      <sv:property sv:name="text" sv:type="String">
        <sv:value>ePortfolio</sv:value>
      </sv:property>
    </sv:node>
    <sv:node sv:name="03">
      <sv:property sv:name="jcr:primaryType" sv:type="Name">
        <sv:value>mgnl:component</sv:value>
      </sv:property>
      <sv:property sv:name="jcr:uuid" sv:type="String">
        <sv:value>7a31e7d3-6a19-4212-a624-93a48379dc18</sv:value>
      </sv:property>
      <sv:property sv:name="jcr:createdBy" sv:type="String">
        <sv:value>admin</sv:value>
      </sv:property>
      <sv:property sv:name="link" sv:type="String">
        <sv:value>http://mycatalog.txstate.edu/</sv:value>
      </sv:property>
      <sv:property sv:name="mgnl:activationStatus" sv:type="Boolean">
        <sv:value>true</sv:value>
      </sv:property>
      <sv:property sv:name="mgnl:created" sv:type="Date">
        <sv:value>2015-11-06T12:49:57.530-06:00</sv:value>
      </sv:property>
      <sv:property sv:name="mgnl:createdBy" sv:type="String">
        <sv:value>a_f269</sv:value>
      </sv:property>
      <sv:property sv:name="mgnl:lastActivated" sv:type="Date">
        <sv:value>2016-02-15T11:30:00.800-06:00</sv:value>
      </sv:property>
      <sv:property sv:name="mgnl:lastActivatedBy" sv:type="String">
        <sv:value>superuser</sv:value>
      </sv:property>
      <sv:property sv:name="mgnl:lastModified" sv:type="Date">
        <sv:value>2015-11-06T12:49:57.530-06:00</sv:value>
      </sv:property>
      <sv:property sv:name="mgnl:lastModifiedBy" sv:type="String">
        <sv:value>a_f269</sv:value>
      </sv:property>
      <sv:property sv:name="mgnl:template" sv:type="String">
        <sv:value>gato-template:components/link</sv:value>
      </sv:property>
      <sv:property sv:name="text" sv:type="String">
        <sv:value>Catalogs</sv:value>
      </sv:property>
    </sv:node>
    <sv:node sv:name="04">
      <sv:property sv:name="jcr:primaryType" sv:type="Name">
        <sv:value>mgnl:component</sv:value>
      </sv:property>
      <sv:property sv:name="jcr:uuid" sv:type="String">
        <sv:value>50c29881-4510-4578-bbf7-4723d472f1f8</sv:value>
      </sv:property>
      <sv:property sv:name="jcr:createdBy" sv:type="String">
        <sv:value>admin</sv:value>
      </sv:property>
      <sv:property sv:name="link" sv:type="String">
        <sv:value>http://txstate.doublemap.com/map/</sv:value>
      </sv:property>
      <sv:property sv:name="mgnl:activationStatus" sv:type="Boolean">
        <sv:value>true</sv:value>
      </sv:property>
      <sv:property sv:name="mgnl:created" sv:type="Date">
        <sv:value>2015-11-06T12:49:57.710-06:00</sv:value>
      </sv:property>
      <sv:property sv:name="mgnl:createdBy" sv:type="String">
        <sv:value>a_f269</sv:value>
      </sv:property>
      <sv:property sv:name="mgnl:lastActivated" sv:type="Date">
        <sv:value>2016-02-15T11:30:00.800-06:00</sv:value>
      </sv:property>
      <sv:property sv:name="mgnl:lastActivatedBy" sv:type="String">
        <sv:value>superuser</sv:value>
      </sv:property>
      <sv:property sv:name="mgnl:lastModified" sv:type="Date">
        <sv:value>2015-11-06T12:49:57.710-06:00</sv:value>
      </sv:property>
      <sv:property sv:name="mgnl:lastModifiedBy" sv:type="String">
        <sv:value>a_f269</sv:value>
      </sv:property>
      <sv:property sv:name="mgnl:template" sv:type="String">
        <sv:value>gato-template:components/link</sv:value>
      </sv:property>
      <sv:property sv:name="text" sv:type="String">
        <sv:value>Shuttle Tracker</sv:value>
      </sv:property>
    </sv:node>
  </sv:node>
  <sv:node sv:name="footerLinksPrimary">
    <sv:property sv:name="jcr:primaryType" sv:type="Name">
      <sv:value>mgnl:content</sv:value>
    </sv:property>
    <sv:property sv:name="jcr:mixinTypes" sv:type="Name" sv:multiple="true">
      <sv:value>mix:lockable</sv:value>
    </sv:property>
    <sv:property sv:name="jcr:uuid" sv:type="String">
      <sv:value>2e3f573d-1678-47dc-9778-ea1a7a571053</sv:value>
    </sv:property>
    <sv:property sv:name="jcr:createdBy" sv:type="String">
      <sv:value>admin</sv:value>
    </sv:property>
    <sv:property sv:name="mgnl:activationStatus" sv:type="Boolean">
      <sv:value>true</sv:value>
    </sv:property>
    <sv:property sv:name="mgnl:created" sv:type="Date">
      <sv:value>2015-08-27T16:31:35.512-05:00</sv:value>
    </sv:property>
    <sv:property sv:name="mgnl:createdBy" sv:type="String">
      <sv:value>a_f269</sv:value>
    </sv:property>
    <sv:property sv:name="mgnl:lastActivated" sv:type="Date">
      <sv:value>2016-02-01T09:43:15.134-06:00</sv:value>
    </sv:property>
    <sv:property sv:name="mgnl:lastActivatedBy" sv:type="String">
      <sv:value>superuser</sv:value>
    </sv:property>
    <sv:property sv:name="mgnl:lastModified" sv:type="Date">
      <sv:value>2016-03-25T14:58:10.221-05:00</sv:value>
    </sv:property>
    <sv:property sv:name="mgnl:lastModifiedBy" sv:type="String">
      <sv:value>a_f269</sv:value>
    </sv:property>
    <sv:property sv:name="text" sv:type="String">
      <sv:value>Footer Links (Primary)</sv:value>
    </sv:property>
    <sv:node sv:name="0">
      <sv:property sv:name="jcr:primaryType" sv:type="Name">
        <sv:value>mgnl:component</sv:value>
      </sv:property>
      <sv:property sv:name="jcr:uuid" sv:type="String">
        <sv:value>d59fd728-804e-4e23-b8cd-b18a1ce23615</sv:value>
      </sv:property>
      <sv:property sv:name="jcr:createdBy" sv:type="String">
        <sv:value>admin</sv:value>
      </sv:property>
      <sv:property sv:name="link" sv:type="String">
        <sv:value>http://www.txstate.edu/about</sv:value>
      </sv:property>
      <sv:property sv:name="mgnl:activationStatus" sv:type="Boolean">
        <sv:value>true</sv:value>
      </sv:property>
      <sv:property sv:name="mgnl:comment" sv:type="String">
        <sv:value/>
      </sv:property>
      <sv:property sv:name="mgnl:created" sv:type="Date">
        <sv:value>2015-08-27T16:31:35.512-05:00</sv:value>
      </sv:property>
      <sv:property sv:name="mgnl:createdBy" sv:type="String">
        <sv:value>a_f269</sv:value>
      </sv:property>
      <sv:property sv:name="mgnl:lastActivated" sv:type="Date">
        <sv:value>2016-02-01T09:43:15.135-06:00</sv:value>
      </sv:property>
      <sv:property sv:name="mgnl:lastActivatedBy" sv:type="String">
        <sv:value>superuser</sv:value>
      </sv:property>
      <sv:property sv:name="mgnl:lastModified" sv:type="Date">
        <sv:value>2016-03-25T14:56:44.840-05:00</sv:value>
      </sv:property>
      <sv:property sv:name="mgnl:lastModifiedBy" sv:type="String">
        <sv:value>a_f269</sv:value>
      </sv:property>
      <sv:property sv:name="mgnl:template" sv:type="String">
        <sv:value>gato-template:components/link</sv:value>
      </sv:property>
      <sv:property sv:name="text" sv:type="String">
        <sv:value>About Texas State</sv:value>
      </sv:property>
    </sv:node>
    <sv:node sv:name="02">
      <sv:property sv:name="jcr:primaryType" sv:type="Name">
        <sv:value>mgnl:component</sv:value>
      </sv:property>
      <sv:property sv:name="jcr:uuid" sv:type="String">
        <sv:value>8f0b77b1-a6d9-4103-b0ff-5956d5cbfdd1</sv:value>
      </sv:property>
      <sv:property sv:name="jcr:createdBy" sv:type="String">
        <sv:value>admin</sv:value>
      </sv:property>
      <sv:property sv:name="link" sv:type="String">
        <sv:value>http://www.txstate.edu/about/about-this-site</sv:value>
      </sv:property>
      <sv:property sv:name="mgnl:activationStatus" sv:type="Boolean">
        <sv:value>true</sv:value>
      </sv:property>
      <sv:property sv:name="mgnl:created" sv:type="Date">
        <sv:value>2015-08-27T16:31:35.512-05:00</sv:value>
      </sv:property>
      <sv:property sv:name="mgnl:createdBy" sv:type="String">
        <sv:value>a_f269</sv:value>
      </sv:property>
      <sv:property sv:name="mgnl:lastActivated" sv:type="Date">
        <sv:value>2016-02-01T09:43:15.135-06:00</sv:value>
      </sv:property>
      <sv:property sv:name="mgnl:lastActivatedBy" sv:type="String">
        <sv:value>superuser</sv:value>
      </sv:property>
      <sv:property sv:name="mgnl:lastModified" sv:type="Date">
        <sv:value>2016-03-25T14:56:44.840-05:00</sv:value>
      </sv:property>
      <sv:property sv:name="mgnl:lastModifiedBy" sv:type="String">
        <sv:value>a_f269</sv:value>
      </sv:property>
      <sv:property sv:name="mgnl:template" sv:type="String">
        <sv:value>gato-template:components/link</sv:value>
      </sv:property>
      <sv:property sv:name="text" sv:type="String">
        <sv:value>About This Site</sv:value>
      </sv:property>
    </sv:node>
    <sv:node sv:name="00">
      <sv:property sv:name="jcr:primaryType" sv:type="Name">
        <sv:value>mgnl:component</sv:value>
      </sv:property>
      <sv:property sv:name="jcr:uuid" sv:type="String">
        <sv:value>9f27d461-1594-4fe4-b839-421421d266be</sv:value>
      </sv:property>
      <sv:property sv:name="jcr:createdBy" sv:type="String">
        <sv:value>admin</sv:value>
      </sv:property>
      <sv:property sv:name="link" sv:type="String">
        <sv:value>http://www.emergencyinfo.txstate.edu/</sv:value>
      </sv:property>
      <sv:property sv:name="mgnl:activationStatus" sv:type="Boolean">
        <sv:value>true</sv:value>
      </sv:property>
      <sv:property sv:name="mgnl:created" sv:type="Date">
        <sv:value>2015-08-27T16:31:35.512-05:00</sv:value>
      </sv:property>
      <sv:property sv:name="mgnl:createdBy" sv:type="String">
        <sv:value>a_f269</sv:value>
      </sv:property>
      <sv:property sv:name="mgnl:lastActivated" sv:type="Date">
        <sv:value>2016-02-01T09:43:15.135-06:00</sv:value>
      </sv:property>
      <sv:property sv:name="mgnl:lastActivatedBy" sv:type="String">
        <sv:value>superuser</sv:value>
      </sv:property>
      <sv:property sv:name="mgnl:lastModified" sv:type="Date">
        <sv:value>2016-03-25T14:56:44.840-05:00</sv:value>
      </sv:property>
      <sv:property sv:name="mgnl:lastModifiedBy" sv:type="String">
        <sv:value>a_f269</sv:value>
      </sv:property>
      <sv:property sv:name="mgnl:template" sv:type="String">
        <sv:value>gato-template:components/link</sv:value>
      </sv:property>
      <sv:property sv:name="text" sv:type="String">
        <sv:value>Emergency Info</sv:value>
      </sv:property>
    </sv:node>
    <sv:node sv:name="01">
      <sv:property sv:name="jcr:primaryType" sv:type="Name">
        <sv:value>mgnl:component</sv:value>
      </sv:property>
      <sv:property sv:name="jcr:uuid" sv:type="String">
        <sv:value>03453db4-8fc9-4595-8b94-842df6f44aa7</sv:value>
      </sv:property>
      <sv:property sv:name="jcr:createdBy" sv:type="String">
        <sv:value>admin</sv:value>
      </sv:property>
      <sv:property sv:name="link" sv:type="String">
        <sv:value>https://jobs.hr.txstate.edu/</sv:value>
      </sv:property>
      <sv:property sv:name="mgnl:activationStatus" sv:type="Boolean">
        <sv:value>true</sv:value>
      </sv:property>
      <sv:property sv:name="mgnl:created" sv:type="Date">
        <sv:value>2015-08-27T16:31:35.512-05:00</sv:value>
      </sv:property>
      <sv:property sv:name="mgnl:createdBy" sv:type="String">
        <sv:value>a_f269</sv:value>
      </sv:property>
      <sv:property sv:name="mgnl:lastActivated" sv:type="Date">
        <sv:value>2016-02-01T09:43:15.135-06:00</sv:value>
      </sv:property>
      <sv:property sv:name="mgnl:lastActivatedBy" sv:type="String">
        <sv:value>superuser</sv:value>
      </sv:property>
      <sv:property sv:name="mgnl:lastModified" sv:type="Date">
        <sv:value>2016-03-25T14:56:44.840-05:00</sv:value>
      </sv:property>
      <sv:property sv:name="mgnl:lastModifiedBy" sv:type="String">
        <sv:value>a_f269</sv:value>
      </sv:property>
      <sv:property sv:name="mgnl:template" sv:type="String">
        <sv:value>gato-template:components/link</sv:value>
      </sv:property>
      <sv:property sv:name="text" sv:type="String">
        <sv:value>Job Opportunities</sv:value>
      </sv:property>
    </sv:node>
    <sv:node sv:name="03">
      <sv:property sv:name="jcr:primaryType" sv:type="Name">
        <sv:value>mgnl:component</sv:value>
      </sv:property>
      <sv:property sv:name="jcr:uuid" sv:type="String">
        <sv:value>1856a726-64f2-4d55-b0d7-795bbe6610c5</sv:value>
      </sv:property>
      <sv:property sv:name="jcr:createdBy" sv:type="String">
        <sv:value>admin</sv:value>
      </sv:property>
      <sv:property sv:name="link" sv:type="String">
        <sv:value>http://search.txstate.edu/</sv:value>
      </sv:property>
      <sv:property sv:name="mgnl:activationStatus" sv:type="Boolean">
        <sv:value>true</sv:value>
      </sv:property>
      <sv:property sv:name="mgnl:created" sv:type="Date">
        <sv:value>2015-08-27T16:31:35.512-05:00</sv:value>
      </sv:property>
      <sv:property sv:name="mgnl:createdBy" sv:type="String">
        <sv:value>a_f269</sv:value>
      </sv:property>
      <sv:property sv:name="mgnl:lastActivated" sv:type="Date">
        <sv:value>2016-02-01T09:43:15.135-06:00</sv:value>
      </sv:property>
      <sv:property sv:name="mgnl:lastActivatedBy" sv:type="String">
        <sv:value>superuser</sv:value>
      </sv:property>
      <sv:property sv:name="mgnl:lastModified" sv:type="Date">
        <sv:value>2016-03-25T14:56:44.840-05:00</sv:value>
      </sv:property>
      <sv:property sv:name="mgnl:lastModifiedBy" sv:type="String">
        <sv:value>a_f269</sv:value>
      </sv:property>
      <sv:property sv:name="mgnl:template" sv:type="String">
        <sv:value>gato-template:components/link</sv:value>
      </sv:property>
      <sv:property sv:name="text" sv:type="String">
        <sv:value>Search Texas State</sv:value>
      </sv:property>
    </sv:node>
  </sv:node>
  <sv:node sv:name="footerLinksSecondary">
    <sv:property sv:name="jcr:primaryType" sv:type="Name">
      <sv:value>mgnl:content</sv:value>
    </sv:property>
    <sv:property sv:name="jcr:mixinTypes" sv:type="Name" sv:multiple="true">
      <sv:value>mix:lockable</sv:value>
    </sv:property>
    <sv:property sv:name="jcr:uuid" sv:type="String">
      <sv:value>f0e9fb8f-4a77-48c7-bc34-62443d364495</sv:value>
    </sv:property>
    <sv:property sv:name="jcr:createdBy" sv:type="String">
      <sv:value>admin</sv:value>
    </sv:property>
    <sv:property sv:name="mgnl:activationStatus" sv:type="Boolean">
      <sv:value>false</sv:value>
    </sv:property>
    <sv:property sv:name="mgnl:created" sv:type="Date">
      <sv:value>2016-03-25T14:56:13.796-05:00</sv:value>
    </sv:property>
    <sv:property sv:name="mgnl:createdBy" sv:type="String">
      <sv:value>a_f269</sv:value>
    </sv:property>
    <sv:property sv:name="mgnl:lastActivated" sv:type="Date">
      <sv:value>2016-03-25T14:56:13.797-05:00</sv:value>
    </sv:property>
    <sv:property sv:name="mgnl:lastActivatedBy" sv:type="String">
      <sv:value>a_f269</sv:value>
    </sv:property>
    <sv:property sv:name="mgnl:lastModified" sv:type="Date">
      <sv:value>2016-03-25T14:58:21.334-05:00</sv:value>
    </sv:property>
    <sv:property sv:name="mgnl:lastModifiedBy" sv:type="String">
      <sv:value>a_f269</sv:value>
    </sv:property>
    <sv:property sv:name="text" sv:type="String">
      <sv:value>Footer Links (Secondary)</sv:value>
    </sv:property>
    <sv:node sv:name="02">
      <sv:property sv:name="jcr:primaryType" sv:type="Name">
        <sv:value>mgnl:component</sv:value>
      </sv:property>
      <sv:property sv:name="jcr:uuid" sv:type="String">
        <sv:value>11e06873-3a38-4498-8cb8-61bb9e49df70</sv:value>
      </sv:property>
      <sv:property sv:name="jcr:createdBy" sv:type="String">
        <sv:value>admin</sv:value>
      </sv:property>
      <sv:property sv:name="link" sv:type="String">
        <sv:value>http://www.txstate.edu/about/about-this-site</sv:value>
      </sv:property>
      <sv:property sv:name="mgnl:activationStatus" sv:type="Boolean">
        <sv:value>false</sv:value>
      </sv:property>
      <sv:property sv:name="mgnl:created" sv:type="Date">
        <sv:value>2016-03-25T14:56:13.796-05:00</sv:value>
      </sv:property>
      <sv:property sv:name="mgnl:createdBy" sv:type="String">
        <sv:value>a_f269</sv:value>
      </sv:property>
      <sv:property sv:name="mgnl:lastActivated" sv:type="Date">
        <sv:value>2016-03-25T14:56:13.797-05:00</sv:value>
      </sv:property>
      <sv:property sv:name="mgnl:lastActivatedBy" sv:type="String">
        <sv:value>a_f269</sv:value>
      </sv:property>
      <sv:property sv:name="mgnl:lastModified" sv:type="Date">
        <sv:value>2016-03-25T14:59:23.682-05:00</sv:value>
      </sv:property>
      <sv:property sv:name="mgnl:lastModifiedBy" sv:type="String">
        <sv:value>a_f269</sv:value>
      </sv:property>
      <sv:property sv:name="mgnl:template" sv:type="String">
        <sv:value>gato-template:components/link</sv:value>
      </sv:property>
      <sv:property sv:name="text" sv:type="String">
        <sv:value>About This Site</sv:value>
      </sv:property>
    </sv:node>
    <sv:node sv:name="0">
      <sv:property sv:name="jcr:primaryType" sv:type="Name">
        <sv:value>mgnl:component</sv:value>
      </sv:property>
      <sv:property sv:name="jcr:uuid" sv:type="String">
        <sv:value>d6229a07-5aa1-4cb0-8ab7-6cd080a567e0</sv:value>
      </sv:property>
      <sv:property sv:name="jcr:createdBy" sv:type="String">
        <sv:value>admin</sv:value>
      </sv:property>
      <sv:property sv:name="link" sv:type="String">
        <sv:value>http://www.txstate.edu/admissions#apply</sv:value>
      </sv:property>
      <sv:property sv:name="mgnl:activationStatus" sv:type="Boolean">
        <sv:value>false</sv:value>
      </sv:property>
      <sv:property sv:name="mgnl:comment" sv:type="String">
        <sv:value/>
      </sv:property>
      <sv:property sv:name="mgnl:created" sv:type="Date">
        <sv:value>2016-03-25T14:56:13.796-05:00</sv:value>
      </sv:property>
      <sv:property sv:name="mgnl:createdBy" sv:type="String">
        <sv:value>a_f269</sv:value>
      </sv:property>
      <sv:property sv:name="mgnl:lastActivated" sv:type="Date">
        <sv:value>2016-03-25T14:56:13.797-05:00</sv:value>
      </sv:property>
      <sv:property sv:name="mgnl:lastActivatedBy" sv:type="String">
        <sv:value>a_f269</sv:value>
      </sv:property>
      <sv:property sv:name="mgnl:lastModified" sv:type="Date">
        <sv:value>2016-03-25T14:59:09.212-05:00</sv:value>
      </sv:property>
      <sv:property sv:name="mgnl:lastModifiedBy" sv:type="String">
        <sv:value>a_f269</sv:value>
      </sv:property>
      <sv:property sv:name="mgnl:template" sv:type="String">
        <sv:value>gato-template:components/link</sv:value>
      </sv:property>
      <sv:property sv:name="text" sv:type="String">
        <sv:value>Apply Now</sv:value>
      </sv:property>
    </sv:node>
    <sv:node sv:name="00">
      <sv:property sv:name="jcr:primaryType" sv:type="Name">
        <sv:value>mgnl:component</sv:value>
      </sv:property>
      <sv:property sv:name="jcr:uuid" sv:type="String">
        <sv:value>2af03423-cd3e-4386-b8b8-691150c235a2</sv:value>
      </sv:property>
      <sv:property sv:name="jcr:createdBy" sv:type="String">
        <sv:value>admin</sv:value>
      </sv:property>
      <sv:property sv:name="link" sv:type="String">
        <sv:value>http://www.emergencyinfo.txstate.edu/</sv:value>
      </sv:property>
      <sv:property sv:name="mgnl:activationStatus" sv:type="Boolean">
        <sv:value>false</sv:value>
      </sv:property>
      <sv:property sv:name="mgnl:created" sv:type="Date">
        <sv:value>2016-03-25T14:56:13.796-05:00</sv:value>
      </sv:property>
      <sv:property sv:name="mgnl:createdBy" sv:type="String">
        <sv:value>a_f269</sv:value>
      </sv:property>
      <sv:property sv:name="mgnl:lastActivated" sv:type="Date">
        <sv:value>2016-03-25T14:56:13.797-05:00</sv:value>
      </sv:property>
      <sv:property sv:name="mgnl:lastActivatedBy" sv:type="String">
        <sv:value>a_f269</sv:value>
      </sv:property>
      <sv:property sv:name="mgnl:lastModified" sv:type="Date">
        <sv:value>2016-03-25T14:56:37.861-05:00</sv:value>
      </sv:property>
      <sv:property sv:name="mgnl:lastModifiedBy" sv:type="String">
        <sv:value>a_f269</sv:value>
      </sv:property>
      <sv:property sv:name="mgnl:template" sv:type="String">
        <sv:value>gato-template:components/link</sv:value>
      </sv:property>
      <sv:property sv:name="text" sv:type="String">
        <sv:value>Emergency Info</sv:value>
      </sv:property>
    </sv:node>
    <sv:node sv:name="01">
      <sv:property sv:name="jcr:primaryType" sv:type="Name">
        <sv:value>mgnl:component</sv:value>
      </sv:property>
      <sv:property sv:name="jcr:uuid" sv:type="String">
        <sv:value>5a0ea23a-c90f-4203-9a0e-fe210b613aa4</sv:value>
      </sv:property>
      <sv:property sv:name="jcr:createdBy" sv:type="String">
        <sv:value>admin</sv:value>
      </sv:property>
      <sv:property sv:name="link" sv:type="String">
        <sv:value>https://jobs.hr.txstate.edu/</sv:value>
      </sv:property>
      <sv:property sv:name="mgnl:activationStatus" sv:type="Boolean">
        <sv:value>false</sv:value>
      </sv:property>
      <sv:property sv:name="mgnl:created" sv:type="Date">
        <sv:value>2016-03-25T14:56:13.796-05:00</sv:value>
      </sv:property>
      <sv:property sv:name="mgnl:createdBy" sv:type="String">
        <sv:value>a_f269</sv:value>
      </sv:property>
      <sv:property sv:name="mgnl:lastActivated" sv:type="Date">
        <sv:value>2016-03-25T14:56:13.798-05:00</sv:value>
      </sv:property>
      <sv:property sv:name="mgnl:lastActivatedBy" sv:type="String">
        <sv:value>a_f269</sv:value>
      </sv:property>
      <sv:property sv:name="mgnl:lastModified" sv:type="Date">
        <sv:value>2016-03-25T14:56:37.861-05:00</sv:value>
      </sv:property>
      <sv:property sv:name="mgnl:lastModifiedBy" sv:type="String">
        <sv:value>a_f269</sv:value>
      </sv:property>
      <sv:property sv:name="mgnl:template" sv:type="String">
        <sv:value>gato-template:components/link</sv:value>
      </sv:property>
      <sv:property sv:name="text" sv:type="String">
        <sv:value>Job Opportunities</sv:value>
      </sv:property>
    </sv:node>
    <sv:node sv:name="03">
      <sv:property sv:name="jcr:primaryType" sv:type="Name">
        <sv:value>mgnl:component</sv:value>
      </sv:property>
      <sv:property sv:name="jcr:uuid" sv:type="String">
        <sv:value>96642c3d-844e-481b-99c4-110f02addf19</sv:value>
      </sv:property>
      <sv:property sv:name="jcr:createdBy" sv:type="String">
        <sv:value>admin</sv:value>
      </sv:property>
      <sv:property sv:name="link" sv:type="String">
        <sv:value>http://search.txstate.edu/</sv:value>
      </sv:property>
      <sv:property sv:name="mgnl:activationStatus" sv:type="Boolean">
        <sv:value>false</sv:value>
      </sv:property>
      <sv:property sv:name="mgnl:created" sv:type="Date">
        <sv:value>2016-03-25T14:56:13.796-05:00</sv:value>
      </sv:property>
      <sv:property sv:name="mgnl:createdBy" sv:type="String">
        <sv:value>a_f269</sv:value>
      </sv:property>
      <sv:property sv:name="mgnl:lastActivated" sv:type="Date">
        <sv:value>2016-03-25T14:56:13.798-05:00</sv:value>
      </sv:property>
      <sv:property sv:name="mgnl:lastActivatedBy" sv:type="String">
        <sv:value>a_f269</sv:value>
      </sv:property>
      <sv:property sv:name="mgnl:lastModified" sv:type="Date">
        <sv:value>2016-03-25T14:56:37.861-05:00</sv:value>
      </sv:property>
      <sv:property sv:name="mgnl:lastModifiedBy" sv:type="String">
        <sv:value>a_f269</sv:value>
      </sv:property>
      <sv:property sv:name="mgnl:template" sv:type="String">
        <sv:value>gato-template:components/link</sv:value>
      </sv:property>
      <sv:property sv:name="text" sv:type="String">
        <sv:value>Search Texas State</sv:value>
      </sv:property>
    </sv:node>
  </sv:node>
</sv:node>
