<?xml version="1.0" encoding="UTF-8"?>
<sv:node sv:name="rjc94" xmlns:sv="http://www.jcp.org/jcr/sv/1.0" xmlns:xsi="http://www.w3.org/2001/XMLSchema-instance">
  <sv:property sv:name="jcr:primaryType" sv:type="Name">
    <sv:value>mgnl:user</sv:value>
  </sv:property>
  <sv:property sv:name="jcr:mixinTypes" sv:type="Name" sv:multiple="true">
    <sv:value>mix:lockable</sv:value>
  </sv:property>
  <sv:property sv:name="jcr:uuid" sv:type="String">
    <sv:value>ebe7d969-11eb-4323-907a-9df94b4622c1</sv:value>
  </sv:property>
  <sv:property sv:name="email" sv:type="String">
    <sv:value>rjc94@txstate.edu</sv:value>
  </sv:property>
  <sv:property sv:name="enabled" sv:type="Boolean">
    <sv:value>true</sv:value>
  </sv:property>
  <sv:property sv:name="jcr:createdBy" sv:type="String">
    <sv:value>admin</sv:value>
  </sv:property>
  <sv:property sv:name="jcrName" sv:type="String">
    <sv:value>rjc94</sv:value>
  </sv:property>
  <sv:property sv:name="language" sv:type="String">
    <sv:value>en</sv:value>
  </sv:property>
  <sv:property sv:name="mgnl:created" sv:type="Date">
    <sv:value>2016-02-02T16:17:23.672-06:00</sv:value>
  </sv:property>
  <sv:property sv:name="mgnl:createdBy" sv:type="String">
    <sv:value>superuser</sv:value>
  </sv:property>
  <sv:property sv:name="mgnl:lastModified" sv:type="Date">
    <sv:value>2016-02-02T16:17:40.351-06:00</sv:value>
  </sv:property>
  <sv:property sv:name="mgnl:lastModifiedBy" sv:type="String">
    <sv:value>superuser</sv:value>
  </sv:property>
  <sv:property sv:name="name" sv:type="String">
    <sv:value>rjc94</sv:value>
  </sv:property>
  <sv:property sv:name="pswd" sv:type="String">
    <sv:value>$2a$12$68dARhYQ0pzbXMbX/EyEmeEmFI6e8PhXdXCYYBJ973tfh4Tj/jRQq</sv:value>
  </sv:property>
  <sv:property sv:name="title" sv:type="String">
    <sv:value>Rachel J Canfield</sv:value>
  </sv:property>
  <sv:node sv:name="acl_users">
    <sv:property sv:name="jcr:primaryType" sv:type="Name">
      <sv:value>mgnl:contentNode</sv:value>
    </sv:property>
    <sv:property sv:name="jcr:uuid" sv:type="String">
      <sv:value>98ccabdf-6637-4bc3-8eb5-57125b2113fe</sv:value>
    </sv:property>
    <sv:property sv:name="jcr:createdBy" sv:type="String">
      <sv:value>admin</sv:value>
    </sv:property>
    <sv:property sv:name="mgnl:created" sv:type="Date">
      <sv:value>2016-02-02T16:17:24.059-06:00</sv:value>
    </sv:property>
    <sv:property sv:name="mgnl:createdBy" sv:type="String">
      <sv:value>superuser</sv:value>
    </sv:property>
    <sv:property sv:name="mgnl:lastModified" sv:type="Date">
      <sv:value>2016-02-02T16:17:24.059-06:00</sv:value>
    </sv:property>
    <sv:property sv:name="mgnl:lastModifiedBy" sv:type="String">
      <sv:value>superuser</sv:value>
    </sv:property>
    <sv:node sv:name="0">
      <sv:property sv:name="jcr:primaryType" sv:type="Name">
        <sv:value>mgnl:contentNode</sv:value>
      </sv:property>
      <sv:property sv:name="jcr:uuid" sv:type="String">
        <sv:value>d78ebc1d-d4a3-4e3a-b66e-49b2a73dffb3</sv:value>
      </sv:property>
      <sv:property sv:name="jcr:createdBy" sv:type="String">
        <sv:value>admin</sv:value>
      </sv:property>
      <sv:property sv:name="mgnl:created" sv:type="Date">
        <sv:value>2016-02-02T16:17:24.059-06:00</sv:value>
      </sv:property>
      <sv:property sv:name="mgnl:createdBy" sv:type="String">
        <sv:value>superuser</sv:value>
      </sv:property>
      <sv:property sv:name="mgnl:lastModified" sv:type="Date">
        <sv:value>2016-02-02T16:17:24.059-06:00</sv:value>
      </sv:property>
      <sv:property sv:name="mgnl:lastModifiedBy" sv:type="String">
        <sv:value>superuser</sv:value>
      </sv:property>
      <sv:property sv:name="path" sv:type="String">
        <sv:value>/admin/rjc94</sv:value>
      </sv:property>
      <sv:property sv:name="permissions" sv:type="Long">
        <sv:value>8</sv:value>
      </sv:property>
    </sv:node>
    <sv:node sv:name="00">
      <sv:property sv:name="jcr:primaryType" sv:type="Name">
        <sv:value>mgnl:contentNode</sv:value>
      </sv:property>
      <sv:property sv:name="jcr:uuid" sv:type="String">
        <sv:value>08fe2bc8-46e4-47de-88fe-a1f1ae188e23</sv:value>
      </sv:property>
      <sv:property sv:name="jcr:createdBy" sv:type="String">
        <sv:value>admin</sv:value>
      </sv:property>
      <sv:property sv:name="mgnl:created" sv:type="Date">
        <sv:value>2016-02-02T16:17:24.060-06:00</sv:value>
      </sv:property>
      <sv:property sv:name="mgnl:createdBy" sv:type="String">
        <sv:value>superuser</sv:value>
      </sv:property>
      <sv:property sv:name="mgnl:lastModified" sv:type="Date">
        <sv:value>2016-02-02T16:17:24.060-06:00</sv:value>
      </sv:property>
      <sv:property sv:name="mgnl:lastModifiedBy" sv:type="String">
        <sv:value>superuser</sv:value>
      </sv:property>
      <sv:property sv:name="path" sv:type="String">
        <sv:value>/admin/rjc94/email</sv:value>
      </sv:property>
      <sv:property sv:name="permissions" sv:type="Long">
        <sv:value>63</sv:value>
      </sv:property>
    </sv:node>
    <sv:node sv:name="01">
      <sv:property sv:name="jcr:primaryType" sv:type="Name">
        <sv:value>mgnl:contentNode</sv:value>
      </sv:property>
      <sv:property sv:name="jcr:uuid" sv:type="String">
        <sv:value>87befec2-89cf-43f7-99f3-dfda4ad816f5</sv:value>
      </sv:property>
      <sv:property sv:name="jcr:createdBy" sv:type="String">
        <sv:value>admin</sv:value>
      </sv:property>
      <sv:property sv:name="mgnl:created" sv:type="Date">
        <sv:value>2016-02-02T16:17:24.061-06:00</sv:value>
      </sv:property>
      <sv:property sv:name="mgnl:createdBy" sv:type="String">
        <sv:value>superuser</sv:value>
      </sv:property>
      <sv:property sv:name="mgnl:lastModified" sv:type="Date">
        <sv:value>2016-02-02T16:17:24.061-06:00</sv:value>
      </sv:property>
      <sv:property sv:name="mgnl:lastModifiedBy" sv:type="String">
        <sv:value>superuser</sv:value>
      </sv:property>
      <sv:property sv:name="path" sv:type="String">
        <sv:value>/admin/rjc94/language</sv:value>
      </sv:property>
      <sv:property sv:name="permissions" sv:type="Long">
        <sv:value>63</sv:value>
      </sv:property>
    </sv:node>
    <sv:node sv:name="02">
      <sv:property sv:name="jcr:primaryType" sv:type="Name">
        <sv:value>mgnl:contentNode</sv:value>
      </sv:property>
      <sv:property sv:name="jcr:uuid" sv:type="String">
        <sv:value>c88760d8-cb68-4dd7-a3a0-2d9a7f4afdcb</sv:value>
      </sv:property>
      <sv:property sv:name="jcr:createdBy" sv:type="String">
        <sv:value>admin</sv:value>
      </sv:property>
      <sv:property sv:name="mgnl:created" sv:type="Date">
        <sv:value>2016-02-02T16:17:24.061-06:00</sv:value>
      </sv:property>
      <sv:property sv:name="mgnl:createdBy" sv:type="String">
        <sv:value>superuser</sv:value>
      </sv:property>
      <sv:property sv:name="mgnl:lastModified" sv:type="Date">
        <sv:value>2016-02-02T16:17:24.061-06:00</sv:value>
      </sv:property>
      <sv:property sv:name="mgnl:lastModifiedBy" sv:type="String">
        <sv:value>superuser</sv:value>
      </sv:property>
      <sv:property sv:name="path" sv:type="String">
        <sv:value>/admin/rjc94/lastaccess</sv:value>
      </sv:property>
      <sv:property sv:name="permissions" sv:type="Long">
        <sv:value>63</sv:value>
      </sv:property>
    </sv:node>
    <sv:node sv:name="03">
      <sv:property sv:name="jcr:primaryType" sv:type="Name">
        <sv:value>mgnl:contentNode</sv:value>
      </sv:property>
      <sv:property sv:name="jcr:uuid" sv:type="String">
        <sv:value>a84e2caf-2d58-4309-9360-d433edd060f0</sv:value>
      </sv:property>
      <sv:property sv:name="jcr:createdBy" sv:type="String">
        <sv:value>admin</sv:value>
      </sv:property>
      <sv:property sv:name="mgnl:created" sv:type="Date">
        <sv:value>2016-02-02T16:17:24.062-06:00</sv:value>
      </sv:property>
      <sv:property sv:name="mgnl:createdBy" sv:type="String">
        <sv:value>superuser</sv:value>
      </sv:property>
      <sv:property sv:name="mgnl:lastModified" sv:type="Date">
        <sv:value>2016-02-02T16:17:24.062-06:00</sv:value>
      </sv:property>
      <sv:property sv:name="mgnl:lastModifiedBy" sv:type="String">
        <sv:value>superuser</sv:value>
      </sv:property>
      <sv:property sv:name="path" sv:type="String">
        <sv:value>/admin/rjc94/pswd</sv:value>
      </sv:property>
      <sv:property sv:name="permissions" sv:type="Long">
        <sv:value>63</sv:value>
      </sv:property>
    </sv:node>
    <sv:node sv:name="04">
      <sv:property sv:name="jcr:primaryType" sv:type="Name">
        <sv:value>mgnl:contentNode</sv:value>
      </sv:property>
      <sv:property sv:name="jcr:uuid" sv:type="String">
        <sv:value>70d8d7fd-a600-41fe-a400-2df2171eee98</sv:value>
      </sv:property>
      <sv:property sv:name="jcr:createdBy" sv:type="String">
        <sv:value>admin</sv:value>
      </sv:property>
      <sv:property sv:name="mgnl:created" sv:type="Date">
        <sv:value>2016-02-02T16:17:24.063-06:00</sv:value>
      </sv:property>
      <sv:property sv:name="mgnl:createdBy" sv:type="String">
        <sv:value>superuser</sv:value>
      </sv:property>
      <sv:property sv:name="mgnl:lastModified" sv:type="Date">
        <sv:value>2016-02-02T16:17:24.063-06:00</sv:value>
      </sv:property>
      <sv:property sv:name="mgnl:lastModifiedBy" sv:type="String">
        <sv:value>superuser</sv:value>
      </sv:property>
      <sv:property sv:name="path" sv:type="String">
        <sv:value>/admin/rjc94/title</sv:value>
      </sv:property>
      <sv:property sv:name="permissions" sv:type="Long">
        <sv:value>63</sv:value>
      </sv:property>
    </sv:node>
  </sv:node>
  <sv:node sv:name="roles">
    <sv:property sv:name="jcr:primaryType" sv:type="Name">
      <sv:value>mgnl:contentNode</sv:value>
    </sv:property>
    <sv:property sv:name="jcr:uuid" sv:type="String">
      <sv:value>3adc120d-1db8-4820-b577-026e3547219e</sv:value>
    </sv:property>
    <sv:property sv:name="0" sv:type="String">
      <sv:value>adddfaa5-0f00-4a01-9664-ed5cfd0fdd0f</sv:value>
    </sv:property>
    <sv:property sv:name="00" sv:type="String">
      <sv:value>bc2046da-b3d5-4cf5-9847-c2b6dbe145ff</sv:value>
    </sv:property>
    <sv:property sv:name="jcr:createdBy" sv:type="String">
      <sv:value>admin</sv:value>
    </sv:property>
  </sv:node>
</sv:node>
